OuterRail/__init__.py
OuterRail/configuration.py
OuterRail/api/__init__.py
OuterRail/api/api_client.py
OuterRail/api/api_response.py
OuterRail/api/assets_api.py
OuterRail/api/exceptions.py
OuterRail/api/experiment_runs_api.py
OuterRail/api/experiment_templates_api.py
OuterRail/api/experiments_api.py
OuterRail/api/rest.py
OuterRail/instances/__init__.py
OuterRail/instances/dataset.py
OuterRail/instances/experiment.py
OuterRail/instances/experiment_run.py
OuterRail/instances/experiment_template.py
OuterRail/managers/__init__.py
OuterRail/managers/asset_manager.py
OuterRail/managers/experiment_manager.py
OuterRail/managers/experiment_run_manager.py
OuterRail/managers/experiment_template_manager.py
OuterRail/models/__init__.py
OuterRail/models/address.py
OuterRail/models/aio_d_entry_read.py
OuterRail/models/asset_cardinality.py
OuterRail/models/asset_schema.py
OuterRail/models/contact_read.py
OuterRail/models/dataset_size.py
OuterRail/models/distribution.py
OuterRail/models/environment_var.py
OuterRail/models/environment_var_def.py
OuterRail/models/geo.py
OuterRail/models/location.py
OuterRail/models/ml_model.py
OuterRail/models/note.py
OuterRail/models/platform.py
OuterRail/models/publication.py
OuterRail/models/run_state.py
OuterRail/models/runnable_distribution.py
OuterRail/models/task_type.py
OuterRail/models/text.py
outerrail-1.2.3.post1.dist-info/licenses/LICENSE
outerrail-1.2.3.post1.dist-info/METADATA
outerrail-1.2.3.post1.dist-info/WHEEL
outerrail-1.2.3.post1.dist-info/top_level.txt
outerrail-1.2.3.post1.dist-info/RECORD
