Metadata-Version: 2.4
Name: OuterRail
Version: 1.2.3.post1
Summary: AIoD - RAIL. SDK for the RAIL service of the AI on Demand platform.
Author-email: Jozef Barut <jozef.barut@intern.kinit.sk>
License-Expression: MIT
Project-URL: repository, https://github.com/aiondemand/aiod-rail
Project-URL: issues, https://github.com/aiondemand/aiod-rail/issues
Project-URL: aIoD-platform, https://www.ai4europe.eu
Project-URL: RAIL-platform, https://rail.aiod.i3a.es/docs/about>
Keywords: SDK,AIoD,RAIL,Machine Learning,ML Experiments
Classifier: Programming Language :: Python :: 3
Classifier: Operating System :: OS Independent
Requires-Python: >=3.11
License-File: LICENSE
Requires-Dist: urllib3>=1.25.3
Requires-Dist: python-dateutil>=2.8.2
Requires-Dist: pydantic>=2
Requires-Dist: typing-extensions>=4.7.1
Requires-Dist: python-keycloak
Requires-Dist: pyjwt
Requires-Dist: tomlkit
Dynamic: license-file
